pyhttpadapter/__init__.py
pyhttpadapter/adp_config.py
pyhttpadapter/api_request.py
pyhttpadapter/api_request_adapter.py
pyhttpadapter/pyhttpadapter.py
pyhttpadapter-5.0.0.dist-info/METADATA
pyhttpadapter-5.0.0.dist-info/WHEEL
pyhttpadapter-5.0.0.dist-info/top_level.txt
pyhttpadapter-5.0.0.dist-info/RECORD
